pyky_package/__init__.py
pyky_package/ccakem.py
pyky_package/cpake.py
pyky_package/indcpa.py
pyky_package/ntt.py
pyky_package/params.py
pyky_package/poly.py
pyky_package/prf.py
pyky_package/test_ccakem.py
pyky_package/test_cpake.py
pyky_package/test_indcpa.py
pyky_package/test_ntt.py
pyky_package/test_poly.py
pyky_package/test_prf.py
pyky_package/test_util.py
pyky_package/util.py
pyky-1.0.2.dist-info/METADATA
pyky-1.0.2.dist-info/WHEEL
pyky-1.0.2.dist-info/top_level.txt
pyky-1.0.2.dist-info/RECORD
