Metadata-Version: 2.2
Name: pyky
Version: 1.0.2
Summary: A Python implementation of Kyber Post-Quantum KEM
Home-page: https://github.com/asdfjkl/pyky
Author: Erhan
Author-email: erhan@example.com
Classifier: Programming Language :: Python :: 3
Classifier: License :: OSI Approved :: MIT License
Classifier: Operating System :: OS Independent
Requires-Python: >=3.7
Requires-Dist: numpy
Requires-Dist: pycryptodome
Dynamic: author
Dynamic: author-email
Dynamic: classifier
Dynamic: description
Dynamic: description-content-type
Dynamic: home-page
Dynamic: requires-dist
Dynamic: requires-python
Dynamic: summary
